netscan_TD4B-1.0.4.dist-info/METADATA
netscan_TD4B-1.0.4.dist-info/WHEEL
netscan_TD4B-1.0.4.dist-info/license_files/LICENSE
netscan/__init__.py
netscan/netscan.cpython-38-darwin.so
netscan_TD4B-1.0.4.dist-info/RECORD
