Metadata-Version: 2.1
Name: netscan_TD4B
Version: 1.0.4
Classifier: Programming Language :: Rust
Classifier: Programming Language :: Python :: Implementation :: CPython
Classifier: Programming Language :: Python :: Implementation :: PyPy
License-File: LICENSE
Summary: This is an API adaption to the Original RustScan, which extends it's functionality for use as a native Python module e.g. Extension Module.
Author-email: TD4B <edwin.twest@gmail.com>
Requires-Python: >=3.7
